an_symlinksutility/__init__.py
an_symlinksutility/symlinksutility.py
an_symlinksutility-0.1.2.dist-info/LICENSE
an_symlinksutility-0.1.2.dist-info/METADATA
an_symlinksutility-0.1.2.dist-info/WHEEL
an_symlinksutility-0.1.2.dist-info/top_level.txt
an_symlinksutility-0.1.2.dist-info/RECORD
