Metadata-Version: 2.1
Name: an_symlinksutility
Version: 0.1.2
Summary: A package for an_symlinksutility.
Home-page: https://github.com/Atsushi888/Atsushi888
Author: Atsushi888
Author-email: Atsushi888 <vtgrotxu@gmail.com>
Project-URL: Homepage, https://github.com/Atsushi888/an_symlinksutility
Project-URL: Repository, https://github.com/Atsushi888/an_symlinksutility
Requires-Python: >=3.6
License-File: LICENSE
Requires-Dist: an-EnvManager
